Metadata-Version: 1.0
Name: gau-bi-distributions
Version: 0.2
Summary: Gaussian and Binomial distributions
Home-page: UNKNOWN
Author: Morufdeen Atilola
Author-email: atilolamorufdeen@gmail.com
License: UNKNOWN
Platform: UNKNOWN
